setup.py
mysql_util/__init__.py
mysql_util/mysql_util.py
mysql_util.egg-info/PKG-INFO
mysql_util.egg-info/SOURCES.txt
mysql_util.egg-info/dependency_links.txt
mysql_util.egg-info/top_level.txt