Metadata-Version: 1.1
Name: mysql_util
Version: 0.0.1
Summary: An demonstration of how to create, document, and publish to the cheese shop a5 pypi.org.
Home-page: UNKNOWN
Author: 9wfox
Author-email: 568628130@qq.com
License: BSD
Keywords: mysql_util mysql mysql utility
Platform: UNKNOWN
Classifier: Development Status :: 3 - Alpha
Classifier: Topic :: Utilities
Classifier: License :: OSI Approved :: BSD License
